orbipy/__init__.py
orbipy/correction.py
orbipy/corrections.py
orbipy/diff_corr.py
orbipy/directions.py
orbipy/events.py
orbipy/extrapolator.py
orbipy/integrators.py
orbipy/interpolators.py
orbipy/lines.py
orbipy/manifold.py
orbipy/mapper.py
orbipy/model_builder.py
orbipy/models.py
orbipy/multiprocessor.py
orbipy/plotter.py
orbipy/scaler.py
orbipy/solout.py
orbipy/station_keeping.py
orbipy/stepper.py
orbipy/data/crtbp_constants.csv
orbipy/data/hlyapunov_sel1.csv
orbipy/data/families/HLY_L1_Earth-Moon (default).csv
orbipy/data/families/HLY_L1_Sun-Earth (default).csv
orbipy/data/families/HLY_L2_Earth-Moon (default).csv
orbipy/data/families/HLY_L2_Sun-Earth (default).csv
orbipy/data/families/PR_HLY_L1_Sun-Earth (default).npy
orbipy/data/families/SP_HLY_L1_Sun-Earth (default).csv
orbipy-0.2.5.dist-info/LICENCE
orbipy-0.2.5.dist-info/METADATA
orbipy-0.2.5.dist-info/WHEEL
orbipy-0.2.5.dist-info/top_level.txt
orbipy-0.2.5.dist-info/RECORD
