Metadata-Version: 2.1
Name: orbipy
Version: 0.2.5
Summary: Extensive orbital dynamics research tool for CRTBP and beyond
Home-page: https://bitbucket.org/stas_bober/orbipy
Author: Bober S.A.
Author-email: stas.bober@gmail.com
License: MIT
Platform: UNKNOWN
Classifier: Development Status :: 3 - Alpha
Classifier: Programming Language :: Python :: 3
Classifier: License :: OSI Approved :: MIT License
Classifier: Operating System :: OS Independent
Requires-Python: >=3.6
Requires-Dist: numpy (>=1.15.2)
Requires-Dist: scipy (>=1.1.0)
Requires-Dist: pandas (>=0.23.4)
Requires-Dist: matplotlib (>=3.0.0)
Requires-Dist: numba (>=0.39.0)
